hcloud/__init__.py
hcloud/_client.py
hcloud/_exceptions.py
hcloud/_version.py
hcloud/py.typed
hcloud/actions/__init__.py
hcloud/actions/client.py
hcloud/actions/domain.py
hcloud/certificates/__init__.py
hcloud/certificates/client.py
hcloud/certificates/domain.py
hcloud/core/__init__.py
hcloud/core/client.py
hcloud/core/domain.py
hcloud/datacenters/__init__.py
hcloud/datacenters/client.py
hcloud/datacenters/domain.py
hcloud/deprecation/__init__.py
hcloud/deprecation/domain.py
hcloud/exp/__init__.py
hcloud/exp/zone.py
hcloud/firewalls/__init__.py
hcloud/firewalls/client.py
hcloud/firewalls/domain.py
hcloud/floating_ips/__init__.py
hcloud/floating_ips/client.py
hcloud/floating_ips/domain.py
hcloud/helpers/__init__.py
hcloud/helpers/labels.py
hcloud/images/__init__.py
hcloud/images/client.py
hcloud/images/domain.py
hcloud/isos/__init__.py
hcloud/isos/client.py
hcloud/isos/domain.py
hcloud/load_balancer_types/__init__.py
hcloud/load_balancer_types/client.py
hcloud/load_balancer_types/domain.py
hcloud/load_balancers/__init__.py
hcloud/load_balancers/client.py
hcloud/load_balancers/domain.py
hcloud/locations/__init__.py
hcloud/locations/client.py
hcloud/locations/domain.py
hcloud/metrics/__init__.py
hcloud/metrics/domain.py
hcloud/networks/__init__.py
hcloud/networks/client.py
hcloud/networks/domain.py
hcloud/placement_groups/__init__.py
hcloud/placement_groups/client.py
hcloud/placement_groups/domain.py
hcloud/primary_ips/__init__.py
hcloud/primary_ips/client.py
hcloud/primary_ips/domain.py
hcloud/rdns/__init__.py
hcloud/rdns/domain.py
hcloud/server_types/__init__.py
hcloud/server_types/client.py
hcloud/server_types/domain.py
hcloud/servers/__init__.py
hcloud/servers/client.py
hcloud/servers/domain.py
hcloud/ssh_keys/__init__.py
hcloud/ssh_keys/client.py
hcloud/ssh_keys/domain.py
hcloud/storage_box_types/__init__.py
hcloud/storage_box_types/client.py
hcloud/storage_box_types/domain.py
hcloud/storage_boxes/__init__.py
hcloud/storage_boxes/client.py
hcloud-2.14.0.dist-info/licenses/LICENSE
hcloud-2.14.0.dist-info/METADATA
hcloud-2.14.0.dist-info/WHEEL
hcloud-2.14.0.dist-info/top_level.txt
hcloud-2.14.0.dist-info/RECORD
