Metadata-Version: 2.4
Name: hcloud
Version: 2.14.0
Summary: Official Hetzner Cloud python library
Home-page: https://github.com/hetznercloud/hcloud-python
Author: Hetzner Cloud GmbH
Author-email: support-cloud@hetzner.com
License: MIT
Project-URL: Bug Tracker, https://github.com/hetznercloud/hcloud-python/issues
Project-URL: Documentation, https://hcloud-python.readthedocs.io/en/stable/
Project-URL: Changelog, https://github.com/hetznercloud/hcloud-python/blob/main/CHANGELOG.md
Project-URL: Source Code, https://github.com/hetznercloud/hcloud-python
Keywords: hcloud hetzner cloud
Classifier: Development Status :: 5 - Production/Stable
Classifier: Intended Audience :: Developers
Classifier: Natural Language :: English
Classifier: Programming Language :: Python :: 3
Classifier: Programming Language :: Python :: 3.10
Classifier: Programming Language :: Python :: 3.11
Classifier: Programming Language :: Python :: 3.12
Classifier: Programming Language :: Python :: 3.13
Classifier: Programming Language :: Python :: 3.14
Requires-Python: >=3.10
License-File: LICENSE
Requires-Dist: python-dateutil>=2.7.5
Requires-Dist: requests>=2.20
Provides-Extra: docs
Requires-Dist: sphinx<8.3,>=8; extra == "docs"
Requires-Dist: sphinx-rtd-theme<3.1,>=3; extra == "docs"
Requires-Dist: myst-parser<4.1,>=4; extra == "docs"
Requires-Dist: watchdog<6.1,>=6; extra == "docs"
Provides-Extra: test
Requires-Dist: coverage<7.14,>=7.13; extra == "test"
Requires-Dist: pylint<4.1,>=4; extra == "test"
Requires-Dist: pytest<9.1,>=9; extra == "test"
Requires-Dist: pytest-cov<7.1,>=7; extra == "test"
Requires-Dist: mypy<1.20,>=1.19; extra == "test"
Requires-Dist: types-python-dateutil; extra == "test"
Requires-Dist: types-requests; extra == "test"
Dynamic: author
Dynamic: author-email
Dynamic: classifier
Dynamic: description
Dynamic: description-content-type
Dynamic: home-page
Dynamic: keywords
Dynamic: license
Dynamic: license-file
Dynamic: project-url
Dynamic: provides-extra
Dynamic: requires-dist
Dynamic: requires-python
Dynamic: summary
